{
"id": 207,
"info": "== Script ID 207 == a9800",
"sections": {
	"class": "java.util.LinkedHashMap",
	"254": {
		"id": 254,
		"instructions": [
			{
				"address": 12,
				"opcode": "endSection",
				"lineNumber": 34211
			}
		]
	},
	"11": {
		"id": 11,
		"instructions": [
			{
				"address": 14,
				"opcode": "if",
				"args": [
					"trigger(225)",
					"==",
					"false",
					"then",
					"30"
				],
				"lineNumber": 34213
			},
			{
				"address": 26,
				"opcode": "jumpTo",
				"args": [
					"4652"
				],
				"lineNumber": 34214
			},
			{
				"address": 30,
				"opcode": "if",
				"args": [
					"trigger(246)",
					"==",
					"false",
					"then",
					"46"
				],
				"lineNumber": 34215
			},
			{
				"address": 42,
				"opcode": "jumpTo",
				"args": [
					"2448"
				],
				"lineNumber": 34216
			},
			{
				"address": 46,
				"opcode": "if",
				"args": [
					"trigger(74)",
					"==",
					"false",
					"then",
					"62"
				],
				"lineNumber": 34217
			},
			{
				"address": 58,
				"opcode": "jumpTo",
				"args": [
					"1114"
				],
				"lineNumber": 34218
			},
			{
				"address": 62,
				"opcode": "setTrigger",
				"args": [
					"74"
				],
				"lineNumber": 34219
			},
			{
				"address": 66,
				"opcode": "setDialogOwner",
				"args": [
					"11"
				],
				"lineNumber": 34220
			},
			{
				"address": 68,
				"opcode": "showTextbox",
				"args": [
					"Hi,",
					"do",
					"you",
					"need",
					"any",
					"Meat?\\n"
				],
				"lineNumber": 34221
			},
			{
				"address": 124,
				"opcode": "showTextbox",
				"args": [
					"Oh,",
					"I",
					"haven't",
					"told",
					"you\\nanything",
					"about",
					"this.\\n"
				],
				"lineNumber": 34222
			},
			{
				"address": 216,
				"opcode": "showTextbox",
				"args": [
					"This",
					"is",
					"a",
					"Meat",
					"farm.\\nWe",
					"grow",
					"Meat",
					"for",
					"everyone.\\n"
				],
				"lineNumber": 34223
			},
			{
				"address": 316,
				"opcode": "setDialogOwner",
				"args": [
					"253"
				],
				"lineNumber": 34224
			},
			{
				"address": 318,
				"opcode": "showTextbox",
				"args": [
					"You",
					"grow",
					"Meat",
					"on",
					"a",
					"farm?\\n"
				],
				"lineNumber": 34225
			},
			{
				"address": 372,
				"opcode": "setDialogOwner",
				"args": [
					"11"
				],
				"lineNumber": 34226
			},
			{
				"address": 374,
				"opcode": "showTextbox",
				"args": [
					"Yeah,",
					"why?\\n"
				],
				"lineNumber": 34227
			},
			{
				"address": 400,
				"opcode": "setDialogOwner",
				"args": [
					"253"
				],
				"lineNumber": 34228
			},
			{
				"address": 402,
				"opcode": "showTextbox",
				"args": [
					"Well...",
					"nothing\\n"
				],
				"lineNumber": 34229
			},
			{
				"address": 438,
				"opcode": "setDialogOwner",
				"args": [
					"11"
				],
				"lineNumber": 34230
			},
			{
				"address": 440,
				"opcode": "showTextbox",
				"args": [
					"Jiji",
					"and",
					"I've",
					"decided",
					"to\\ngive",
					"you",
					"three",
					"pieces",
					"of\\nMeat",
					"daily,",
					"<LIGHTBLUE><PLAYER><WHITE>.\\n"
				],
				"lineNumber": 34231
			},
			{
				"address": 578,
				"opcode": "showTextbox",
				"args": [
					"Here's",
					"your",
					"Meat",
					"for",
					"today.\\n"
				],
				"lineNumber": 34232
			},
			{
				"address": 638,
				"opcode": "if",
				"args": [
					"item(38)",
					"<",
					"99",
					"then",
					"762"
				],
				"lineNumber": 34233
			},
			{
				"address": 652,
				"opcode": "setDialogOwner",
				"args": [
					"11"
				],
				"lineNumber": 34234
			},
			{
				"address": 654,
				"opcode": "showTextbox",
				"args": [
					"You",
					"got",
					"too",
					"much",
					"Meat.\\nYou",
					"don't",
					"need",
					"any",
					"today.\\n"
				],
				"lineNumber": 34235
			},
			{
				"address": 756,
				"opcode": "setPStat",
				"args": [
					"31",
					"1"
				],
				"lineNumber": 34236
			},
			{
				"address": 760,
				"opcode": "endSection",
				"lineNumber": 34237
			},
			{
				"address": 762,
				"opcode": "if",
				"args": [
					"item(38)",
					"<",
					"97",
					"then",
					"970"
				],
				"lineNumber": 34238
			},
			{
				"address": 776,
				"opcode": "setDialogOwner",
				"args": [
					"11"
				],
				"lineNumber": 34239
			},
			{
				"address": 778,
				"opcode": "showTextbox",
				"args": [
					"You",
					"got",
					"too",
					"much",
					"Meat.",
					"I'll\\ntake",
					"what",
					"you",
					"can't",
					"hold.\\n"
				],
				"lineNumber": 34240
			},
			{
				"address": 890,
				"opcode": "giveItem",
				"args": [
					"38",
					"3"
				],
				"lineNumber": 34241
			},
			{
				"address": 894,
				"opcode": "setDialogOwner",
				"args": [
					"255"
				],
				"lineNumber": 34242
			},
			{
				"address": 896,
				"opcode": "showTextbox",
				"args": [
					"I",
					"got",
					"three",
					"pieces\\nof",
					"<LIGHTBLUE>Meat<WHITE>!\\n"
				],
				"lineNumber": 34243
			},
			{
				"address": 960,
				"opcode": "setTrigger",
				"args": [
					"74"
				],
				"lineNumber": 34244
			},
			{
				"address": 964,
				"opcode": "setPStat",
				"args": [
					"31",
					"0"
				],
				"lineNumber": 34245
			},
			{
				"address": 968,
				"opcode": "endSection",
				"lineNumber": 34246
			},
			{
				"address": 970,
				"opcode": "giveItem",
				"args": [
					"38",
					"3"
				],
				"lineNumber": 34247
			},
			{
				"address": 974,
				"opcode": "if",
				"args": [
					"trigger(0)",
					"==",
					"false",
					"then",
					"1042"
				],
				"lineNumber": 34248
			},
			{
				"address": 986,
				"opcode": "setDialogOwner",
				"args": [
					"11"
				],
				"lineNumber": 34249
			},
			{
				"address": 988,
				"opcode": "showTextbox",
				"args": [
					"You",
					"got",
					"too",
					"many",
					"Items.\\n"
				],
				"lineNumber": 34250
			},
			{
				"address": 1040,
				"opcode": "endSection",
				"lineNumber": 34251
			},
			{
				"address": 1042,
				"opcode": "setDialogOwner",
				"args": [
					"255"
				],
				"lineNumber": 34252
			},
			{
				"address": 1044,
				"opcode": "showTextbox",
				"args": [
					"I",
					"got",
					"three",
					"pieces",
					"of\\n<LIGHTBLUE>Meat<WHITE>!\\n"
				],
				"lineNumber": 34253
			},
			{
				"address": 1108,
				"opcode": "setPStat",
				"args": [
					"31",
					"0"
				],
				"lineNumber": 34254
			},
			{
				"address": 1112,
				"opcode": "endSection",
				"lineNumber": 34255
			},
			{
				"address": 1114,
				"opcode": "storeRandom",
				"args": [
					"110",
					"9"
				],
				"lineNumber": 34256
			},
			{
				"address": 1118,
				"opcode": "if",
				"args": [
					"pstat(31)",
					"<",
					"1",
					"OR",
					"pstat(110)",
					">",
					"0",
					"then",
					"1268"
				],
				"lineNumber": 34257
			},
			{
				"address": 1134,
				"opcode": "setDialogOwner",
				"args": [
					"11"
				],
				"lineNumber": 34258
			},
			{
				"address": 1136,
				"opcode": "showTextbox",
				"args": [
					"We",
					"harvested",
					"a",
					"lot",
					"of",
					"Meat\\ntoday!",
					"We'll",
					"give",
					"you\\nfive",
					"pieces.\\n"
				],
				"lineNumber": 34259
			},
			{
				"address": 1264,
				"opcode": "jumpTo",
				"args": [
					"1272"
				],
				"lineNumber": 34260
			},
			{
				"address": 1268,
				"opcode": "jumpTo",
				"args": [
					"1750"
				],
				"lineNumber": 34261
			},
			{
				"address": 1272,
				"opcode": "if",
				"args": [
					"item(38)",
					"<",
					"99",
					"then",
					"1340"
				],
				"lineNumber": 34262
			},
			{
				"address": 1286,
				"opcode": "setDialogOwner",
				"args": [
					"11"
				],
				"lineNumber": 34263
			},
			{
				"address": 1288,
				"opcode": "showTextbox",
				"args": [
					"You",
					"got",
					"too",
					"much",
					"Meat.\\n"
				],
				"lineNumber": 34264
			},
			{
				"address": 1338,
				"opcode": "endSection",
				"lineNumber": 34265
			},
			{
				"address": 1340,
				"opcode": "if",
				"args": [
					"item(38)",
					"<",
					"95",
					"then",
					"1550"
				],
				"lineNumber": 34266
			},
			{
				"address": 1354,
				"opcode": "setDialogOwner",
				"args": [
					"11"
				],
				"lineNumber": 34267
			},
			{
				"address": 1356,
				"opcode": "showTextbox",
				"args": [
					"You",
					"got",
					"too",
					"much",
					"Meat.",
					"I'll\\ntake",
					"what",
					"you",
					"can't",
					"hold.\\n"
				],
				"lineNumber": 34268
			},
			{
				"address": 1468,
				"opcode": "giveItem",
				"args": [
					"38",
					"5"
				],
				"lineNumber": 34269
			},
			{
				"address": 1472,
				"opcode": "setDialogOwner",
				"args": [
					"255"
				],
				"lineNumber": 34270
			},
			{
				"address": 1474,
				"opcode": "showTextbox",
				"args": [
					"I",
					"got",
					"a",
					"five",
					"pieces",
					"of\\n<LIGHTBLUE>Meat<WHITE>!\\n"
				],
				"lineNumber": 34271
			},
			{
				"address": 1540,
				"opcode": "setTrigger",
				"args": [
					"74"
				],
				"lineNumber": 34272
			},
			{
				"address": 1544,
				"opcode": "setPStat",
				"args": [
					"31",
					"0"
				],
				"lineNumber": 34273
			},
			{
				"address": 1548,
				"opcode": "endSection",
				"lineNumber": 34274
			},
			{
				"address": 1550,
				"opcode": "giveItem",
				"args": [
					"38",
					"5"
				],
				"lineNumber": 34275
			},
			{
				"address": 1554,
				"opcode": "if",
				"args": [
					"trigger(0)",
					"==",
					"false",
					"then",
					"1622"
				],
				"lineNumber": 34276
			},
			{
				"address": 1566,
				"opcode": "setDialogOwner",
				"args": [
					"11"
				],
				"lineNumber": 34277
			},
			{
				"address": 1568,
				"opcode": "showTextbox",
				"args": [
					"You",
					"got",
					"too",
					"many",
					"Items.\\n"
				],
				"lineNumber": 34278
			},
			{
				"address": 1620,
				"opcode": "endSection",
				"lineNumber": 34279
			},
			{
				"address": 1622,
				"opcode": "setDialogOwner",
				"args": [
					"255"
				],
				"lineNumber": 34280
			},
			{
				"address": 1624,
				"opcode": "showTextbox",
				"args": [
					"I",
					"got",
					"five",
					"pieces",
					"of\\n<LIGHTBLUE>Meat<WHITE>!\\n"
				],
				"lineNumber": 34281
			},
			{
				"address": 1686,
				"opcode": "setDialogOwner",
				"args": [
					"11"
				],
				"lineNumber": 34282
			},
			{
				"address": 1688,
				"opcode": "showTextbox",
				"args": [
					"You'll",
					"get",
					"more",
					"tomorrow.\\n"
				],
				"lineNumber": 34283
			},
			{
				"address": 1744,
				"opcode": "setPStat",
				"args": [
					"31",
					"0"
				],
				"lineNumber": 34284
			},
			{
				"address": 1748,
				"opcode": "endSection",
				"lineNumber": 34285
			},
			{
				"address": 1750,
				"opcode": "if",
				"args": [
					"pstat(31)",
					"<",
					"1",
					"then",
					"1814"
				],
				"lineNumber": 34286
			},
			{
				"address": 1762,
				"opcode": "setDialogOwner",
				"args": [
					"11"
				],
				"lineNumber": 34287
			},
			{
				"address": 1764,
				"opcode": "showTextbox",
				"args": [
					"Here's",
					"today's",
					"Meat.\\n"
				],
				"lineNumber": 34288
			},
			{
				"address": 1810,
				"opcode": "jumpTo",
				"args": [
					"1818"
				],
				"lineNumber": 34289
			},
			{
				"address": 1814,
				"opcode": "jumpTo",
				"args": [
					"2238"
				],
				"lineNumber": 34290
			},
			{
				"address": 1818,
				"opcode": "if",
				"args": [
					"item(38)",
					"<",
					"99",
					"then",
					"1886"
				],
				"lineNumber": 34291
			},
			{
				"address": 1832,
				"opcode": "setDialogOwner",
				"args": [
					"11"
				],
				"lineNumber": 34292
			},
			{
				"address": 1834,
				"opcode": "showTextbox",
				"args": [
					"You",
					"got",
					"too",
					"much",
					"Meat.\\n"
				],
				"lineNumber": 34293
			},
			{
				"address": 1884,
				"opcode": "endSection",
				"lineNumber": 34294
			},
			{
				"address": 1886,
				"opcode": "if",
				"args": [
					"item(38)",
					"<",
					"97",
					"then",
					"2062"
				],
				"lineNumber": 34295
			},
			{
				"address": 1900,
				"opcode": "setDialogOwner",
				"args": [
					"11"
				],
				"lineNumber": 34296
			},
			{
				"address": 1902,
				"opcode": "showTextbox",
				"args": [
					"You",
					"got",
					"too",
					"much",
					"Meat.",
					"I'll\\ntake",
					"what",
					"you",
					"can't",
					"hold.\\n"
				],
				"lineNumber": 34297
			},
			{
				"address": 2014,
				"opcode": "giveItem",
				"args": [
					"38",
					"3"
				],
				"lineNumber": 34298
			},
			{
				"address": 2018,
				"opcode": "setDialogOwner",
				"args": [
					"255"
				],
				"lineNumber": 34299
			},
			{
				"address": 2020,
				"opcode": "showTextbox",
				"args": [
					"I",
					"got",
					"<LIGHTBLUE>Meat<WHITE>!\\n"
				],
				"lineNumber": 34300
			},
			{
				"address": 2052,
				"opcode": "setTrigger",
				"args": [
					"74"
				],
				"lineNumber": 34301
			},
			{
				"address": 2056,
				"opcode": "setPStat",
				"args": [
					"31",
					"0"
				],
				"lineNumber": 34302
			},
			{
				"address": 2060,
				"opcode": "endSection",
				"lineNumber": 34303
			},
			{
				"address": 2062,
				"opcode": "giveItem",
				"args": [
					"38",
					"3"
				],
				"lineNumber": 34304
			},
			{
				"address": 2066,
				"opcode": "if",
				"args": [
					"trigger(0)",
					"==",
					"false",
					"then",
					"2134"
				],
				"lineNumber": 34305
			},
			{
				"address": 2078,
				"opcode": "setDialogOwner",
				"args": [
					"11"
				],
				"lineNumber": 34306
			},
			{
				"address": 2080,
				"opcode": "showTextbox",
				"args": [
					"You",
					"got",
					"too",
					"many",
					"Items.\\n"
				],
				"lineNumber": 34307
			},
			{
				"address": 2132,
				"opcode": "endSection",
				"lineNumber": 34308
			},
			{
				"address": 2134,
				"opcode": "setDialogOwner",
				"args": [
					"255"
				],
				"lineNumber": 34309
			},
			{
				"address": 2136,
				"opcode": "showTextbox",
				"args": [
					"I",
					"got",
					"<LIGHTBLUE>Meat<WHITE>!\\n"
				],
				"lineNumber": 34310
			},
			{
				"address": 2168,
				"opcode": "setDialogOwner",
				"args": [
					"11"
				],
				"lineNumber": 34311
			},
			{
				"address": 2170,
				"opcode": "showTextbox",
				"args": [
					"I'll",
					"give",
					"you",
					"more",
					"tomorrow.\\n"
				],
				"lineNumber": 34312
			},
			{
				"address": 2232,
				"opcode": "setPStat",
				"args": [
					"31",
					"0"
				],
				"lineNumber": 34313
			},
			{
				"address": 2236,
				"opcode": "endSection",
				"lineNumber": 34314
			},
			{
				"address": 2238,
				"opcode": "setDialogOwner",
				"args": [
					"11"
				],
				"lineNumber": 34315
			},
			{
				"address": 2240,
				"opcode": "showTextbox",
				"args": [
					"I",
					"thought",
					"I",
					"gave",
					"you\\ntoday's",
					"Meat.\\n"
				],
				"lineNumber": 34316
			},
			{
				"address": 2314,
				"opcode": "showTextbox",
				"args": [
					"If",
					"you",
					"run",
					"out",
					"of",
					"food,\\ngo",
					"to",
					"Native",
					"Forest",
					"and\\nfind",
					"mushrooms.\\n"
				],
				"lineNumber": 34317
			},
			{
				"address": 2446,
				"opcode": "endSection",
				"lineNumber": 34318
			},
			{
				"address": 2448,
				"opcode": "if",
				"args": [
					"trigger(82)",
					"==",
					"true",
					"then",
					"2910"
				],
				"lineNumber": 34319
			},
			{
				"address": 2460,
				"opcode": "setTrigger",
				"args": [
					"82"
				],
				"lineNumber": 34320
			},
			{
				"address": 2464,
				"opcode": "setDialogOwner",
				"args": [
					"11"
				],
				"lineNumber": 34321
			},
			{
				"address": 2466,
				"opcode": "showTextbox",
				"args": [
					"Hi,",
					"<LIGHTBLUE><PLAYER><WHITE>,",
					"I",
					"expanded\\nmy",
					"Meat",
					"farm.\\n"
				],
				"lineNumber": 34322
			},
			{
				"address": 2538,
				"opcode": "showTextbox",
				"args": [
					"I'll",
					"give",
					"you",
					"three",
					"pieces\\nof",
					"Giant",
					"Meat",
					"a",
					"day.\\n"
				],
				"lineNumber": 34323
			},
			{
				"address": 2638,
				"opcode": "showTextbox",
				"args": [
					"If",
					"you",
					"want",
					"extra,\\nI'll",
					"sell",
					"it",
					"to",
					"you",
					"for\\nfive",
					"hund",
					"bits",
					"each.\\n"
				],
				"lineNumber": 34324
			},
			{
				"address": 2770,
				"opcode": "showTextbox",
				"args": [
					"I'll",
					"be",
					"in",
					"charge",
					"of\\nthis",
					"farm",
					"for",
					"Tanemon.\\nHe's",
					"resting",
					"somewhere.\\n"
				],
				"lineNumber": 34325
			},
			{
				"address": 2910,
				"opcode": "storeRandom",
				"args": [
					"110",
					"9"
				],
				"lineNumber": 34326
			},
			{
				"address": 2914,
				"opcode": "if",
				"args": [
					"pstat(31)",
					"<",
					"1",
					"OR",
					"pstat(110)",
					">",
					"0",
					"then",
					"3006"
				],
				"lineNumber": 34327
			},
			{
				"address": 2930,
				"opcode": "setDialogOwner",
				"args": [
					"11"
				],
				"lineNumber": 34328
			},
			{
				"address": 2932,
				"opcode": "showTextbox",
				"args": [
					"I",
					"harvested",
					"a",
					"lot",
					"of\\nMeat",
					"today!\\n"
				],
				"lineNumber": 34329
			},
			{
				"address": 3002,
				"opcode": "jumpTo",
				"args": [
					"3010"
				],
				"lineNumber": 34330
			},
			{
				"address": 3006,
				"opcode": "jumpTo",
				"args": [
					"3548"
				],
				"lineNumber": 34331
			},
			{
				"address": 3010,
				"opcode": "if",
				"args": [
					"item(39)",
					"<",
					"99",
					"then",
					"3142"
				],
				"lineNumber": 34332
			},
			{
				"address": 3024,
				"opcode": "setDialogOwner",
				"args": [
					"11"
				],
				"lineNumber": 34333
			},
			{
				"address": 3026,
				"opcode": "showTextbox",
				"args": [
					"You",
					"got",
					"too",
					"much",
					"Giant",
					"Meat.\\nYou",
					"don't",
					"need",
					"any",
					"today.\\n"
				],
				"lineNumber": 34334
			},
			{
				"address": 3140,
				"opcode": "endSection",
				"lineNumber": 34335
			},
			{
				"address": 3142,
				"opcode": "if",
				"args": [
					"item(39)",
					"<",
					"95",
					"then",
					"3332"
				],
				"lineNumber": 34336
			},
			{
				"address": 3156,
				"opcode": "setDialogOwner",
				"args": [
					"11"
				],
				"lineNumber": 34337
			},
			{
				"address": 3158,
				"opcode": "showTextbox",
				"args": [
					"You",
					"got",
					"too",
					"much",
					"Giant",
					"Meat.\\nYou",
					"don't",
					"need",
					"any",
					"today.\\n"
				],
				"lineNumber": 34338
			},
			{
				"address": 3272,
				"opcode": "giveItem",
				"args": [
					"39",
					"5"
				],
				"lineNumber": 34339
			},
			{
				"address": 3276,
				"opcode": "setDialogOwner",
				"args": [
					"255"
				],
				"lineNumber": 34340
			},
			{
				"address": 3278,
				"opcode": "showTextbox",
				"args": [
					"I",
					"got",
					"<LIGHTBLUE>Giant",
					"Meat<WHITE>!\\n"
				],
				"lineNumber": 34341
			},
			{
				"address": 3322,
				"opcode": "setTrigger",
				"args": [
					"74"
				],
				"lineNumber": 34342
			},
			{
				"address": 3326,
				"opcode": "setPStat",
				"args": [
					"31",
					"0"
				],
				"lineNumber": 34343
			},
			{
				"address": 3330,
				"opcode": "endSection",
				"lineNumber": 34344
			},
			{
				"address": 3332,
				"opcode": "giveItem",
				"args": [
					"39",
					"5"
				],
				"lineNumber": 34345
			},
			{
				"address": 3336,
				"opcode": "if",
				"args": [
					"trigger(0)",
					"==",
					"false",
					"then",
					"3402"
				],
				"lineNumber": 34346
			},
			{
				"address": 3348,
				"opcode": "showTextbox",
				"args": [
					"You",
					"got",
					"too",
					"many",
					"Items.\\n"
				],
				"lineNumber": 34347
			},
			{
				"address": 3400,
				"opcode": "endSection",
				"lineNumber": 34348
			},
			{
				"address": 3402,
				"opcode": "setDialogOwner",
				"args": [
					"255"
				],
				"lineNumber": 34349
			},
			{
				"address": 3404,
				"opcode": "showTextbox",
				"args": [
					"I",
					"got",
					"five",
					"pieces",
					"of\\n<LIGHTBLUE>Giant",
					"Meat<WHITE>!\\n"
				],
				"lineNumber": 34350
			},
			{
				"address": 3478,
				"opcode": "setDialogOwner",
				"args": [
					"11"
				],
				"lineNumber": 34351
			},
			{
				"address": 3480,
				"opcode": "showTextbox",
				"args": [
					"I'll",
					"give",
					"you",
					"more",
					"tomorrow.\\n"
				],
				"lineNumber": 34352
			},
			{
				"address": 3542,
				"opcode": "setPStat",
				"args": [
					"31",
					"0"
				],
				"lineNumber": 34353
			},
			{
				"address": 3546,
				"opcode": "endSection",
				"lineNumber": 34354
			},
			{
				"address": 3548,
				"opcode": "if",
				"args": [
					"pstat(31)",
					"<",
					"1",
					"then",
					"3660"
				],
				"lineNumber": 34355
			},
			{
				"address": 3560,
				"opcode": "setDialogOwner",
				"args": [
					"11"
				],
				"lineNumber": 34356
			},
			{
				"address": 3562,
				"opcode": "showTextbox",
				"args": [
					"Here's",
					"three",
					"pieces",
					"of\\nGiant",
					"Meat",
					"for",
					"today.\\n"
				],
				"lineNumber": 34357
			},
			{
				"address": 3656,
				"opcode": "jumpTo",
				"args": [
					"3664"
				],
				"lineNumber": 34358
			},
			{
				"address": 3660,
				"opcode": "jumpTo",
				"args": [
					"4148"
				],
				"lineNumber": 34359
			},
			{
				"address": 3664,
				"opcode": "if",
				"args": [
					"item(39)",
					"<",
					"99",
					"then",
					"3794"
				],
				"lineNumber": 34360
			},
			{
				"address": 3678,
				"opcode": "setDialogOwner",
				"args": [
					"11"
				],
				"lineNumber": 34361
			},
			{
				"address": 3680,
				"opcode": "showTextbox",
				"args": [
					"You",
					"got",
					"too",
					"much",
					"Giant",
					"Meat.\\nYou",
					"don't",
					"need",
					"any",
					"today\\n"
				],
				"lineNumber": 34362
			},
			{
				"address": 3792,
				"opcode": "endSection",
				"lineNumber": 34363
			},
			{
				"address": 3794,
				"opcode": "if",
				"args": [
					"item(39)",
					"<",
					"97",
					"then",
					"3994"
				],
				"lineNumber": 34364
			},
			{
				"address": 3808,
				"opcode": "setDialogOwner",
				"args": [
					"11"
				],
				"lineNumber": 34365
			},
			{
				"address": 3810,
				"opcode": "showTextbox",
				"args": [
					"You",
					"got",
					"too",
					"much\\nGiant",
					"Meat.",
					"I'll",
					"take\\nwhat",
					"you",
					"can't",
					"hold.\\n"
				],
				"lineNumber": 34366
			},
			{
				"address": 3934,
				"opcode": "giveItem",
				"args": [
					"39",
					"3"
				],
				"lineNumber": 34367
			},
			{
				"address": 3938,
				"opcode": "setDialogOwner",
				"args": [
					"255"
				],
				"lineNumber": 34368
			},
			{
				"address": 3940,
				"opcode": "showTextbox",
				"args": [
					"I",
					"got",
					"<LIGHTBLUE>Giant",
					"Meat<WHITE>!\\n"
				],
				"lineNumber": 34369
			},
			{
				"address": 3984,
				"opcode": "setTrigger",
				"args": [
					"74"
				],
				"lineNumber": 34370
			},
			{
				"address": 3988,
				"opcode": "setPStat",
				"args": [
					"31",
					"0"
				],
				"lineNumber": 34371
			},
			{
				"address": 3992,
				"opcode": "endSection",
				"lineNumber": 34372
			},
			{
				"address": 3994,
				"opcode": "giveItem",
				"args": [
					"39",
					"3"
				],
				"lineNumber": 34373
			},
			{
				"address": 3998,
				"opcode": "if",
				"args": [
					"trigger(0)",
					"==",
					"false",
					"then",
					"4064"
				],
				"lineNumber": 34374
			},
			{
				"address": 4010,
				"opcode": "showTextbox",
				"args": [
					"You",
					"got",
					"too",
					"many",
					"Items.\\n"
				],
				"lineNumber": 34375
			},
			{
				"address": 4062,
				"opcode": "endSection",
				"lineNumber": 34376
			},
			{
				"address": 4064,
				"opcode": "setDialogOwner",
				"args": [
					"255"
				],
				"lineNumber": 34377
			},
			{
				"address": 4066,
				"opcode": "showTextbox",
				"args": [
					"I",
					"got",
					"three",
					"pieces",
					"of\\n<LIGHTBLUE>Giant",
					"Meat<WHITE>!\\n"
				],
				"lineNumber": 34378
			},
			{
				"address": 4142,
				"opcode": "setPStat",
				"args": [
					"31",
					"0"
				],
				"lineNumber": 34379
			},
			{
				"address": 4146,
				"opcode": "endSection",
				"lineNumber": 34380
			},
			{
				"address": 4148,
				"opcode": "setDialogOwner",
				"args": [
					"11"
				],
				"lineNumber": 34381
			},
			{
				"address": 4150,
				"opcode": "showTextbox",
				"args": [
					"I'll",
					"give",
					"you",
					"more",
					"tomorrow.\\nOr",
					"you",
					"can",
					"buy",
					"more",
					"now.\\nFive",
					"hund",
					"bits",
					"each?\\n"
				],
				"lineNumber": 34382
			},
			{
				"address": 4304,
				"opcode": "setDialogOwner",
				"args": [
					"253"
				],
				"lineNumber": 34383
			},
			{
				"address": 4306,
				"opcode": "setSelection",
				"args": [
					"4350",
					"4608"
				],
				"lineNumber": 34384
			},
			{
				"address": 4312,
				"opcode": "showTextbox",
				"args": [
					"Buy\\nDon't",
					"buy\\n"
				],
				"lineNumber": 34385
			},
			{
				"address": 4344,
				"opcode": "unknown12",
				"args": [
					"0"
				],
				"lineNumber": 34386
			},
			{
				"address": 4346,
				"opcode": "jumpTo",
				"args": [
					"4608"
				],
				"lineNumber": 34387
			},
			{
				"address": 4350,
				"opcode": "if",
				"args": [
					"getMoney",
					">=",
					"500",
					"then",
					"4416"
				],
				"lineNumber": 34388
			},
			{
				"address": 4366,
				"opcode": "setDialogOwner",
				"args": [
					"11"
				],
				"lineNumber": 34389
			},
			{
				"address": 4368,
				"opcode": "showTextbox",
				"args": [
					"You",
					"need",
					"more",
					"money.\\n"
				],
				"lineNumber": 34390
			},
			{
				"address": 4414,
				"opcode": "endSection",
				"lineNumber": 34391
			},
			{
				"address": 4416,
				"opcode": "giveItem",
				"args": [
					"39",
					"1"
				],
				"lineNumber": 34392
			},
			{
				"address": 4420,
				"opcode": "if",
				"args": [
					"trigger(0)",
					"==",
					"false",
					"then",
					"4492"
				],
				"lineNumber": 34393
			},
			{
				"address": 4432,
				"opcode": "showTextbox",
				"args": [
					"You've",
					"got",
					"too",
					"many",
					"Items.\\n"
				],
				"lineNumber": 34394
			},
			{
				"address": 4490,
				"opcode": "endSection",
				"lineNumber": 34395
			},
			{
				"address": 4492,
				"opcode": "reduceMoney",
				"args": [
					"500"
				],
				"lineNumber": 34396
			},
			{
				"address": 4498,
				"opcode": "playSound",
				"args": [
					"1280"
				],
				"lineNumber": 34397
			},
			{
				"address": 4502,
				"opcode": "delay",
				"args": [
					"5"
				],
				"lineNumber": 34398
			},
			{
				"address": 4506,
				"opcode": "setDialogOwner",
				"args": [
					"11"
				],
				"lineNumber": 34399
			},
			{
				"address": 4508,
				"opcode": "showTextbox",
				"args": [
					"Do",
					"you",
					"want",
					"to",
					"buy",
					"more?\\n"
				],
				"lineNumber": 34400
			},
			{
				"address": 4562,
				"opcode": "setDialogOwner",
				"args": [
					"253"
				],
				"lineNumber": 34401
			},
			{
				"address": 4564,
				"opcode": "setSelection",
				"args": [
					"4350",
					"4608"
				],
				"lineNumber": 34402
			},
			{
				"address": 4570,
				"opcode": "showTextbox",
				"args": [
					"Buy\\nDon't",
					"buy\\n"
				],
				"lineNumber": 34403
			},
			{
				"address": 4602,
				"opcode": "unknown12",
				"args": [
					"0"
				],
				"lineNumber": 34404
			},
			{
				"address": 4604,
				"opcode": "jumpTo",
				"args": [
					"4608"
				],
				"lineNumber": 34405
			},
			{
				"address": 4608,
				"opcode": "setDialogOwner",
				"args": [
					"11"
				],
				"lineNumber": 34406
			},
			{
				"address": 4610,
				"opcode": "showTextbox",
				"args": [
					"See",
					"you",
					"tomorrow.\\n"
				],
				"lineNumber": 34407
			},
			{
				"address": 4650,
				"opcode": "endSection",
				"lineNumber": 34408
			},
			{
				"address": 4652,
				"opcode": "if",
				"args": [
					"trigger(186)",
					"==",
					"true",
					"then",
					"5008"
				],
				"lineNumber": 34409
			},
			{
				"address": 4664,
				"opcode": "setTrigger",
				"args": [
					"186"
				],
				"lineNumber": 34410
			},
			{
				"address": 4668,
				"opcode": "setDialogOwner",
				"args": [
					"11"
				],
				"lineNumber": 34411
			},
			{
				"address": 4670,
				"opcode": "showTextbox",
				"args": [
					"Heh,",
					"heh,",
					"heh!\\n<LIGHTBLUE><PLAYER><WHITE>,",
					"look!\\n"
				],
				"lineNumber": 34412
			},
			{
				"address": 4726,
				"opcode": "moveCameraTo",
				"args": [
					"30",
					"-2243",
					"1914"
				],
				"lineNumber": 34413
			},
			{
				"address": 4732,
				"opcode": "waitForEntity",
				"args": [
					"200"
				],
				"lineNumber": 34414
			},
			{
				"address": 4734,
				"opcode": "delay",
				"args": [
					"20"
				],
				"lineNumber": 34415
			},
			{
				"address": 4738,
				"opcode": "moveCameraToEntity",
				"args": [
					"253",
					"20"
				],
				"lineNumber": 34416
			},
			{
				"address": 4742,
				"opcode": "waitForEntity",
				"args": [
					"200"
				],
				"lineNumber": 34417
			},
			{
				"address": 4744,
				"opcode": "setDialogOwner",
				"args": [
					"11"
				],
				"lineNumber": 34418
			},
			{
				"address": 4746,
				"opcode": "showTextbox",
				"args": [
					"We",
					"can",
					"grow",
					"lots",
					"of\\nSirloin.",
					"I'll",
					"give",
					"you\\nthree",
					"Sirloins",
					"a",
					"day.\\n"
				],
				"lineNumber": 34419
			},
			{
				"address": 4880,
				"opcode": "showTextbox",
				"args": [
					"I",
					"also",
					"started",
					"to\\ngrow",
					"rare",
					"veggies!\\nBuy",
					"as",
					"many",
					"as",
					"you",
					"want!\\n"
				],
				"lineNumber": 34420
			},
			{
				"address": 5008,
				"opcode": "storeRandom",
				"args": [
					"110",
					"9"
				],
				"lineNumber": 34421
			},
			{
				"address": 5012,
				"opcode": "if",
				"args": [
					"pstat(31)",
					"<",
					"1",
					"OR",
					"pstat(110)",
					">",
					"0",
					"then",
					"5158"
				],
				"lineNumber": 34422
			},
			{
				"address": 5028,
				"opcode": "setDialogOwner",
				"args": [
					"11"
				],
				"lineNumber": 34423
			},
			{
				"address": 5030,
				"opcode": "showTextbox",
				"args": [
					"I",
					"feel",
					"good",
					"today,\\nso",
					"I'll",
					"give",
					"you",
					"five",
					"pieces\\nof",
					"Sirloin.\\n"
				],
				"lineNumber": 34424
			},
			{
				"address": 5154,
				"opcode": "jumpTo",
				"args": [
					"5162"
				],
				"lineNumber": 34425
			},
			{
				"address": 5158,
				"opcode": "jumpTo",
				"args": [
					"5600"
				],
				"lineNumber": 34426
			},
			{
				"address": 5162,
				"opcode": "if",
				"args": [
					"item(40)",
					"<",
					"99",
					"then",
					"5286"
				],
				"lineNumber": 34427
			},
			{
				"address": 5176,
				"opcode": "setDialogOwner",
				"args": [
					"11"
				],
				"lineNumber": 34428
			},
			{
				"address": 5178,
				"opcode": "showTextbox",
				"args": [
					"You",
					"got",
					"too",
					"much",
					"Sirloin.\\nYou",
					"don't",
					"need",
					"any",
					"today\\n"
				],
				"lineNumber": 34429
			},
			{
				"address": 5284,
				"opcode": "endSection",
				"lineNumber": 34430
			},
			{
				"address": 5286,
				"opcode": "if",
				"args": [
					"item(40)",
					"<",
					"95",
					"then",
					"5412"
				],
				"lineNumber": 34431
			},
			{
				"address": 5300,
				"opcode": "setDialogOwner",
				"args": [
					"11"
				],
				"lineNumber": 34432
			},
			{
				"address": 5302,
				"opcode": "showTextbox",
				"args": [
					"You",
					"got",
					"too",
					"much",
					"Sirloin.\\n"
				],
				"lineNumber": 34433
			},
			{
				"address": 5358,
				"opcode": "giveItem",
				"args": [
					"40",
					"5"
				],
				"lineNumber": 34434
			},
			{
				"address": 5362,
				"opcode": "setDialogOwner",
				"args": [
					"255"
				],
				"lineNumber": 34435
			},
			{
				"address": 5364,
				"opcode": "showTextbox",
				"args": [
					"I",
					"got",
					"<LIGHTBLUE>Sirloin<WHITE>!\\n"
				],
				"lineNumber": 34436
			},
			{
				"address": 5402,
				"opcode": "setTrigger",
				"args": [
					"74"
				],
				"lineNumber": 34437
			},
			{
				"address": 5406,
				"opcode": "setPStat",
				"args": [
					"31",
					"0"
				],
				"lineNumber": 34438
			},
			{
				"address": 5410,
				"opcode": "endSection",
				"lineNumber": 34439
			},
			{
				"address": 5412,
				"opcode": "giveItem",
				"args": [
					"40",
					"5"
				],
				"lineNumber": 34440
			},
			{
				"address": 5416,
				"opcode": "if",
				"args": [
					"trigger(0)",
					"==",
					"false",
					"then",
					"5482"
				],
				"lineNumber": 34441
			},
			{
				"address": 5428,
				"opcode": "showTextbox",
				"args": [
					"You",
					"got",
					"too",
					"many",
					"Items.\\n"
				],
				"lineNumber": 34442
			},
			{
				"address": 5480,
				"opcode": "endSection",
				"lineNumber": 34443
			},
			{
				"address": 5482,
				"opcode": "setDialogOwner",
				"args": [
					"255"
				],
				"lineNumber": 34444
			},
			{
				"address": 5484,
				"opcode": "showTextbox",
				"args": [
					"I",
					"got",
					"five",
					"pieces",
					"of\\n<LIGHTBLUE>Sirloin<WHITE>!\\n"
				],
				"lineNumber": 34445
			},
			{
				"address": 5552,
				"opcode": "setDialogOwner",
				"args": [
					"11"
				],
				"lineNumber": 34446
			},
			{
				"address": 5554,
				"opcode": "showTextbox",
				"args": [
					"See",
					"you",
					"tomorrow!\\n"
				],
				"lineNumber": 34447
			},
			{
				"address": 5594,
				"opcode": "setPStat",
				"args": [
					"31",
					"0"
				],
				"lineNumber": 34448
			},
			{
				"address": 5598,
				"opcode": "endSection",
				"lineNumber": 34449
			},
			{
				"address": 5600,
				"opcode": "if",
				"args": [
					"pstat(31)",
					"<",
					"1",
					"then",
					"5716"
				],
				"lineNumber": 34450
			},
			{
				"address": 5612,
				"opcode": "setDialogOwner",
				"args": [
					"11"
				],
				"lineNumber": 34451
			},
			{
				"address": 5614,
				"opcode": "showTextbox",
				"args": [
					"Here's",
					"today's",
					"portion",
					"of\\nSirloin",
					"times",
					"three!\\n"
				],
				"lineNumber": 34452
			},
			{
				"address": 5712,
				"opcode": "jumpTo",
				"args": [
					"5720"
				],
				"lineNumber": 34453
			},
			{
				"address": 5716,
				"opcode": "jumpTo",
				"args": [
					"6122"
				],
				"lineNumber": 34454
			},
			{
				"address": 5720,
				"opcode": "if",
				"args": [
					"item(40)",
					"<",
					"99",
					"then",
					"5846"
				],
				"lineNumber": 34455
			},
			{
				"address": 5734,
				"opcode": "setDialogOwner",
				"args": [
					"11"
				],
				"lineNumber": 34456
			},
			{
				"address": 5736,
				"opcode": "showTextbox",
				"args": [
					"You",
					"got",
					"too",
					"much",
					"Sirloin.\\nYou",
					"don't",
					"need",
					"any",
					"today.\\n"
				],
				"lineNumber": 34457
			},
			{
				"address": 5844,
				"opcode": "endSection",
				"lineNumber": 34458
			},
			{
				"address": 5846,
				"opcode": "if",
				"args": [
					"item(40)",
					"<",
					"97",
					"then",
					"5972"
				],
				"lineNumber": 34459
			},
			{
				"address": 5860,
				"opcode": "setDialogOwner",
				"args": [
					"11"
				],
				"lineNumber": 34460
			},
			{
				"address": 5862,
				"opcode": "showTextbox",
				"args": [
					"You",
					"got",
					"too",
					"much",
					"Sirloin.\\n"
				],
				"lineNumber": 34461
			},
			{
				"address": 5918,
				"opcode": "giveItem",
				"args": [
					"40",
					"3"
				],
				"lineNumber": 34462
			},
			{
				"address": 5922,
				"opcode": "setDialogOwner",
				"args": [
					"255"
				],
				"lineNumber": 34463
			},
			{
				"address": 5924,
				"opcode": "showTextbox",
				"args": [
					"I",
					"got",
					"<LIGHTBLUE>Sirloin<WHITE>!\\n"
				],
				"lineNumber": 34464
			},
			{
				"address": 5962,
				"opcode": "setTrigger",
				"args": [
					"74"
				],
				"lineNumber": 34465
			},
			{
				"address": 5966,
				"opcode": "setPStat",
				"args": [
					"31",
					"0"
				],
				"lineNumber": 34466
			},
			{
				"address": 5970,
				"opcode": "endSection",
				"lineNumber": 34467
			},
			{
				"address": 5972,
				"opcode": "giveItem",
				"args": [
					"40",
					"3"
				],
				"lineNumber": 34468
			},
			{
				"address": 5976,
				"opcode": "if",
				"args": [
					"trigger(0)",
					"==",
					"false",
					"then",
					"6044"
				],
				"lineNumber": 34469
			},
			{
				"address": 5988,
				"opcode": "setDialogOwner",
				"args": [
					"11"
				],
				"lineNumber": 34470
			},
			{
				"address": 5990,
				"opcode": "showTextbox",
				"args": [
					"You",
					"got",
					"too",
					"many",
					"Items.\\n"
				],
				"lineNumber": 34471
			},
			{
				"address": 6042,
				"opcode": "endSection",
				"lineNumber": 34472
			},
			{
				"address": 6044,
				"opcode": "setDialogOwner",
				"args": [
					"255"
				],
				"lineNumber": 34473
			},
			{
				"address": 6046,
				"opcode": "showTextbox",
				"args": [
					"I",
					"got",
					"three",
					"pieces",
					"of\\n<LIGHTBLUE>Sirloin<WHITE>!\\n"
				],
				"lineNumber": 34474
			},
			{
				"address": 6116,
				"opcode": "setPStat",
				"args": [
					"31",
					"0"
				],
				"lineNumber": 34475
			},
			{
				"address": 6120,
				"opcode": "endSection",
				"lineNumber": 34476
			},
			{
				"address": 6122,
				"opcode": "setDialogOwner",
				"args": [
					"11"
				],
				"lineNumber": 34477
			},
			{
				"address": 6124,
				"opcode": "showTextbox",
				"args": [
					"It's",
					"not",
					"tomorrow",
					"yet!\\nDo",
					"you",
					"want",
					"to",
					"buy",
					"veggies?\\n"
				],
				"lineNumber": 34478
			},
			{
				"address": 6230,
				"opcode": "setDialogOwner",
				"args": [
					"253"
				],
				"lineNumber": 34479
			},
			{
				"address": 6232,
				"opcode": "setSelection",
				"args": [
					"6276",
					"6854"
				],
				"lineNumber": 34480
			},
			{
				"address": 6238,
				"opcode": "showTextbox",
				"args": [
					"Buy\\nDon't",
					"buy\\n"
				],
				"lineNumber": 34481
			},
			{
				"address": 6270,
				"opcode": "unknown12",
				"args": [
					"0"
				],
				"lineNumber": 34482
			},
			{
				"address": 6272,
				"opcode": "jumpTo",
				"args": [
					"6854"
				],
				"lineNumber": 34483
			},
			{
				"address": 6276,
				"opcode": "setDialogOwner",
				"args": [
					"253"
				],
				"lineNumber": 34484
			},
			{
				"address": 6278,
				"opcode": "setSelection",
				"args": [
					"6430",
					"6584",
					"6854"
				],
				"lineNumber": 34485
			},
			{
				"address": 6286,
				"opcode": "showTextbox",
				"args": [
					"Super",
					"Carrot:",
					"five",
					"hund",
					"bits\\nHawk",
					"Radish:",
					"five",
					"hund",
					"bits\\nDon't",
					"buy\\n"
				],
				"lineNumber": 34486
			},
			{
				"address": 6424,
				"opcode": "unknown12",
				"args": [
					"0"
				],
				"lineNumber": 34487
			},
			{
				"address": 6426,
				"opcode": "jumpTo",
				"args": [
					"6854"
				],
				"lineNumber": 34488
			},
			{
				"address": 6430,
				"opcode": "if",
				"args": [
					"getMoney",
					">=",
					"500",
					"then",
					"6510"
				],
				"lineNumber": 34489
			},
			{
				"address": 6446,
				"opcode": "setDialogOwner",
				"args": [
					"11"
				],
				"lineNumber": 34490
			},
			{
				"address": 6448,
				"opcode": "showTextbox",
				"args": [
					"You",
					"don't",
					"got",
					"enough",
					"money.\\n"
				],
				"lineNumber": 34491
			},
			{
				"address": 6508,
				"opcode": "endSection",
				"lineNumber": 34492
			},
			{
				"address": 6510,
				"opcode": "giveItem",
				"args": [
					"41",
					"1"
				],
				"lineNumber": 34493
			},
			{
				"address": 6514,
				"opcode": "if",
				"args": [
					"trigger(0)",
					"==",
					"false",
					"then",
					"6580"
				],
				"lineNumber": 34494
			},
			{
				"address": 6526,
				"opcode": "showTextbox",
				"args": [
					"You",
					"got",
					"too",
					"many",
					"Items!\\n"
				],
				"lineNumber": 34495
			},
			{
				"address": 6578,
				"opcode": "endSection",
				"lineNumber": 34496
			},
			{
				"address": 6580,
				"opcode": "jumpTo",
				"args": [
					"6738"
				],
				"lineNumber": 34497
			},
			{
				"address": 6584,
				"opcode": "if",
				"args": [
					"getMoney",
					">=",
					"500",
					"then",
					"6664"
				],
				"lineNumber": 34498
			},
			{
				"address": 6600,
				"opcode": "setDialogOwner",
				"args": [
					"11"
				],
				"lineNumber": 34499
			},
			{
				"address": 6602,
				"opcode": "showTextbox",
				"args": [
					"You",
					"don't",
					"got",
					"enough",
					"money.\\n"
				],
				"lineNumber": 34500
			},
			{
				"address": 6662,
				"opcode": "endSection",
				"lineNumber": 34501
			},
			{
				"address": 6664,
				"opcode": "giveItem",
				"args": [
					"42",
					"1"
				],
				"lineNumber": 34502
			},
			{
				"address": 6668,
				"opcode": "if",
				"args": [
					"trigger(0)",
					"==",
					"false",
					"then",
					"6734"
				],
				"lineNumber": 34503
			},
			{
				"address": 6680,
				"opcode": "showTextbox",
				"args": [
					"You",
					"got",
					"too",
					"many",
					"Items!\\n"
				],
				"lineNumber": 34504
			},
			{
				"address": 6732,
				"opcode": "endSection",
				"lineNumber": 34505
			},
			{
				"address": 6734,
				"opcode": "jumpTo",
				"args": [
					"6738"
				],
				"lineNumber": 34506
			},
			{
				"address": 6738,
				"opcode": "reduceMoney",
				"args": [
					"500"
				],
				"lineNumber": 34507
			},
			{
				"address": 6744,
				"opcode": "playSound",
				"args": [
					"1280"
				],
				"lineNumber": 34508
			},
			{
				"address": 6748,
				"opcode": "delay",
				"args": [
					"5"
				],
				"lineNumber": 34509
			},
			{
				"address": 6752,
				"opcode": "setDialogOwner",
				"args": [
					"11"
				],
				"lineNumber": 34510
			},
			{
				"address": 6754,
				"opcode": "showTextbox",
				"args": [
					"Do",
					"you",
					"want",
					"to",
					"buy",
					"more?\\n"
				],
				"lineNumber": 34511
			},
			{
				"address": 6808,
				"opcode": "setDialogOwner",
				"args": [
					"253"
				],
				"lineNumber": 34512
			},
			{
				"address": 6810,
				"opcode": "setSelection",
				"args": [
					"6276",
					"6854"
				],
				"lineNumber": 34513
			},
			{
				"address": 6816,
				"opcode": "showTextbox",
				"args": [
					"Buy\\nDon't",
					"buy\\n"
				],
				"lineNumber": 34514
			},
			{
				"address": 6848,
				"opcode": "unknown12",
				"args": [
					"0"
				],
				"lineNumber": 34515
			},
			{
				"address": 6850,
				"opcode": "jumpTo",
				"args": [
					"6854"
				],
				"lineNumber": 34516
			},
			{
				"address": 6854,
				"opcode": "setDialogOwner",
				"args": [
					"11"
				],
				"lineNumber": 34517
			},
			{
				"address": 6856,
				"opcode": "showTextbox",
				"args": [
					"See",
					"ya!\\n"
				],
				"lineNumber": 34518
			},
			{
				"address": 6876,
				"opcode": "endSection",
				"lineNumber": 34519
			}
		]
	}
}
}